app.py
quick_validation.py
visualization.py
gcndesign/__init__.py
gcndesign/_version.py
gcndesign/dataset.py
gcndesign/hypara.py
gcndesign/models.py
gcndesign/pdbutil.py
gcndesign/predictor.py
gcndesign/resfile.py
gcndesign/training.py
gcndesign/params/param_default.pkl
gcndesign/params/param_legacy_06.15.2021
protgcn-1.0.0.dist-info/LICENSE
protgcn-1.0.0.dist-info/METADATA
protgcn-1.0.0.dist-info/WHEEL
protgcn-1.0.0.dist-info/entry_points.txt
protgcn-1.0.0.dist-info/top_level.txt
protgcn-1.0.0.dist-info/RECORD
