Metadata-Version: 2.1
Name: protgcn
Version: 1.0.0
Summary: State-of-the-art protein sequence design using Graph Convolutional Networks
Home-page: https://github.com/your-username/ProtGCN
Author: Mahatir Ahmed Tusher, Anik Saha, Md. Shakil Ahmed
Author-email: protgcn@example.com
License: MIT
Keywords: protgcn,protein design,graph neural networks,bioinformatics
Platform: UNKNOWN
Classifier: Development Status :: 5 - Production/Stable
Classifier: Intended Audience :: Science/Research
Classifier: License :: OSI Approved :: MIT License
Classifier: Operating System :: OS Independent
Classifier: Programming Language :: Python :: 3
Classifier: Programming Language :: Python :: 3.8
Classifier: Programming Language :: Python :: 3.9
Classifier: Programming Language :: Python :: 3.10
Classifier: Programming Language :: Python :: 3.11
Classifier: Topic :: Scientific/Engineering :: Bio-Informatics
Classifier: Topic :: Scientific/Engineering :: Artificial Intelligence
Requires-Python: >=3.8
License-File: LICENSE
Requires-Dist: torch>=1.9.0
Requires-Dist: numpy>=1.19.0
Requires-Dist: pandas>=1.3.0
Requires-Dist: scikit-learn>=1.0.0
Requires-Dist: matplotlib>=3.3.0
Requires-Dist: seaborn>=0.11.0
Requires-Dist: tqdm>=4.60.0
Requires-Dist: flask>=2.0.0
Requires-Dist: werkzeug>=2.0.0
